appfw/__init__.py
appfw/app.py
appfw/app_init.py
appfw/tpl/app.tpl
appfw/tpl/config.tpl
appfw-0.8.3.dist-info/LICENSE
appfw-0.8.3.dist-info/METADATA
appfw-0.8.3.dist-info/WHEEL
appfw-0.8.3.dist-info/entry_points.txt
appfw-0.8.3.dist-info/top_level.txt
appfw-0.8.3.dist-info/RECORD
